Workbook

Sheet Calibration Reference
A1: RISK RATING CALIBRATION GUIDELINES
A3: Risk Rating | B3: PD Range (%) | C3: LGD Range (%) | D3: Typical Application
A4: Excellent | B4: 0.03 - 0.10 | C4: 20 - 25 | D4: Blue chip
A5: Very Good | B5: 0.10 - 0.25 | C5: 25 - 35 | D5: Large corporates
A6: Good | B6: 0.25 - 0.50 | C6: 35 - 45 | D6: Mid-cap companies
A7: Satisfactory | B7: 0.50 - 1.00 | C7: 40 - 50 | D7: SMEs
A8: Acceptable | B8: 1.00 - 2.00 | C8: 45 - 55 | D8: Higher risk
A9: Watch | B9: 2.00 - 5.00 | C9: 50 - 65 | D9: Stressed
A10: Substandard | B10: 5.00 - 10.00 | C10: 60 - 75 | D10: Problem credits

Sheet Portfolio Summary
A2: Metric | B2: Value | C2: Description
A3: Total EAD | B3: ='AIRB Calculation'!D7 -> 200000 | C3: Sum of all exposures
A4: Total RWA | B4: ='AIRB Calculation'!I7 -> 180.74123 | C4: Risk-weighted assets
A5: Capital Required | B5: ='AIRB Calculation'!J7 -> 14.459298 | C5: Minimum capital (8% of RWA)
A6: RWA/EAD Ratio (%) | B6: ='AIRB Calculation'!I7/'AIRB Calculation'!D7*100 -> 0.090370614 | C6: Risk density
A8: REGULATORY MINIMUMS
A9: CET1 (4.5%) | B9: ='AIRB Calculation'!I7*0.045 -> 8.1333552 | C9: Common Equity Tier 1
A10: Tier 1 (6.0%) | B10: ='AIRB Calculation'!I7*0.06 -> 10.844474 | C10: Total Tier 1 capital

Sheet AIRB Calculation
A1: Loan ID | B1: Borrower | C1: Sector | D1: EAD ($) | E1: PD (%) | F1: LGD (%) | G1: M (Yrs) | H1: Correlation | I1: RWA ($) | J1: Capital Req ($) | K1: Notes
A2: L001 | B2: ABC Corp | C2: Manufacturing | D2: 100000 | E2: 0.1 | F2: 45 | G2: 2 | H2: =MIN(0.03+0.12*(1-EXP(-50*E2/100)),0.999) -> 0.035852469 | I2: =D2*((E2/100*F2/100*(1+(H2-1)*0.14)/(1-1.5*0.14))*1.06-E2/100*F2/100)*12.5 -> 90.370614 | J2: =I2*0.08 -> 7.2296491
A3: L002 | B3: XYZ Inc | C3: Retail | D3: 100000 | E3: 0.1 | F3: 45 | G3: 2 | H3: =MIN(0.03+0.12*(1-EXP(-50*E3/100)),0.999) -> 0.035852469 | I3: =D3*((E3/100*F3/100*(1+(H3-1)*0.14)/(1-1.5*0.14))*1.06-E3/100*F3/100)*12.5 -> 90.370614 | J3: =I3*0.08 -> 7.2296491
A4: L003 | B4: Tech Ltd | C4: Technology | H4: =MIN(0.03+0.12*(1-EXP(-50*E4/100)),0.999) -> 0.03 | I4: =D4*((E4/100*F4/100*(1+(H4-1)*0.14)/(1-1.5*0.14))*1.06-E4/100*F4/100)*12.5 -> 0 | J4: =I4*0.08 -> 0
A5: L004 | B5: Bank Loan | C5: Financial | H5: =MIN(0.03+0.12*(1-EXP(-50*E5/100)),0.999) -> 0.03 | I5: =D5*((E5/100*F5/100*(1+(H5-1)*0.14)/(1-1.5*0.14))*1.06-E5/100*F5/100)*12.5 -> 0 | J5: =I5*0.08 -> 0
A6: L005 | B6: Real Estate | C6: Real Estate | H6: =MIN(0.03+0.12*(1-EXP(-50*E6/100)),0.999) -> 0.03 | I6: =D6*((E6/100*F6/100*(1+(H6-1)*0.14)/(1-1.5*0.14))*1.06-E6/100*F6/100)*12.5 -> 0 | J6: =I6*0.08 -> 0
A7: TOTAL | D7: =SUM(D2:D6) -> 200000 | I7: =SUM(I2:I6) -> 180.74123 | J7: =SUM(J2:J6) -> 14.459298

Sheet Instructions
A1: AIRB CREDIT RISK CALCULATION TEMPLATE
A3: OVERVIEW:
A4: Advanced IRB approach for calculating credit risk-weighted assets (RWA) under Basel III
A6: KEY COMPONENTS:
A7: • PD (Probability of Default): 1-year default probability (%)
A8: • LGD (Loss Given Default): Loss percentage if default (%)
A9: • EAD (Exposure at Default): Total exposure amount
A10: • M (Maturity): Time to maturity (1-5 years)
A12: FORMULA: RWA = EAD × [PD×LGD×(1+(M-1)×b)/(1-1.5×b)×1.06 - PD×LGD] × 12.5
A14: INSTRUCTIONS:
A15: 1. Use AIRB Calculation sheet
A16: 2. Enter loan details (gray cells)
... A18: 4. Check Portfolio Summary for totals

Sheet Sheet1
